[
    {
        "name": "ObjectA",
        "coordinate": [
            {
                "x": 40,
                "y": 10,
                "z": 0
            }
        ],
        "isGoal": true,
        "size": 70
    },
    {
        "name": "ObjectB",
        "coordinate": [
            {
                "x": 10,
                "y": 40,
                "z": 0
            }
        ],
        "isGoal": false,
        "size": 50
    },
    {
        "name": "ObjectC",
        "coordinate": [
            {
                "x": 15,
                "y": 60,
                "z": 0
            }
        ],
        "isGoal": false,
        "size": 100
    },
    {
        "name": "ObjectD",
        "coordinate": [
            {
                "x": 80,
                "y": 30,
                "z": 0
            }
        ],
        "isGoal": false,
        "size": 80
    },
    {
        "name": "ObjectE",
        "coordinate": [
            {
                "x": 60,
                "y": 70,
                "z": 0
            }
        ],
        "isGoal": false,
        "size": 20
    },
    {
        "name": "ObjectF",
        "coordinate": [
            {
                "x": 20,
                "y": 20,
                "z": 0
            }
        ],
        "isGoal": false,
        "size": 30
    }
]